<?xml version="1.0" encoding="UTF-8"?>

<!DOCTYPE struts PUBLIC
        "-//Apache Software Foundation//DTD Struts Configuration 2.5//EN"
        "http://struts.apache.org/dtds/struts-2.5.dtd">

<struts>
    <include file="xml/Keyword.xml"/>
    <include file="xml/Publication.xml"/>
    <include file="xml/PublicationType.xml"/>
    <include file="xml/Customer.xml"/>
    <package name="default" extends="tiles-default">
        <result-types>
            <result-type name="tiles" class="org.apache.struts2.views.tiles.TilesResult" default="true"/>
        </result-types>
    </package>
</struts>